tensorflow_enterprise_addons/__init__.py
tensorflow_enterprise_addons/version.py
tensorflow_enterprise_addons/cloud_fit/__init__.py
tensorflow_enterprise_addons/cloud_fit/client.py
tensorflow_enterprise_addons/cloud_fit/client_test.py
tensorflow_enterprise_addons/cloud_fit/integration_test.py
tensorflow_enterprise_addons/cloud_fit/remote.py
tensorflow_enterprise_addons/cloud_fit/remote_test.py
tensorflow_enterprise_addons/cloud_fit/utils.py
tensorflow_enterprise_addons/cloud_fit/utils_test.py
tensorflow_enterprise_addons/cloudtuner/__init__.py
tensorflow_enterprise_addons/cloudtuner/cloud_tuner.py
tensorflow_enterprise_addons/cloudtuner/cloud_tuner_integration_test.py
tensorflow_enterprise_addons/cloudtuner/cloud_tuner_test.py
tensorflow_enterprise_addons/cloudtuner/cloud_tuner_utils.py
tensorflow_enterprise_addons/cloudtuner/cloud_tuner_utils_test.py
tensorflow_enterprise_addons/cloudtuner/optimizer_client.py
tensorflow_enterprise_addons/cloudtuner/optimizer_client_test.py
tensorflow_enterprise_addons/cloudtuner/api/ml_public_google_rest_v1.json
tensorflow_enterprise_addons-0.1.1.dist-info/METADATA
tensorflow_enterprise_addons-0.1.1.dist-info/WHEEL
tensorflow_enterprise_addons-0.1.1.dist-info/top_level.txt
tensorflow_enterprise_addons-0.1.1.dist-info/RECORD
